[{"content":"入选标准 赵一鸣零食店名字里含茶的饮料（无论含不含糖） \n评价标准纯个人，不喜勿看 \n环境全常温（南方沿海夏天温度） \n先贴一张全部有多少的图片（慢慢更新中 感觉我能喝3天） \n￼","id":5,"tAvatar":"https://lain.bgm.tv/r/400/pic/user/l/000/43/65/436585.jpg?r=1677730346&hd=1","tImage":"https://sm.ms/image/5jXVaA81cNgzJtC\" target=\"_blank\" rel=\"nofollow external noopener noreferrer\" class=\"l\"><img src=\"https://s2.loli.net/2024/07/12/5jXVaA81cNgzJtC.jpg","tName":"苺妹","tUid":"mbf","tUrl":"https://bgm.tv/rakuen/topic/group/401918","tid":"401918","time":1720828628142,"title":"20款茶类饮料对比","type":1,"uid":"bangumi_muxi"},{"content":"昨天晚上突然想到“为什么女性向番剧基本暴死”这个问题，就随便找了个群问了一下。 \n让我绷不住的是，有个群竟然有人反问我： \n“排球少年和蓝色监狱还不够成功吗？” \n\n不是，哥们，你管这叫女性向？ \n看的女生多=女性向？ \n男性角色体育番=女性向？ \n\n我当即反驳对方，体育番跟是否为女性向根本没有任何关系。更何况我的指意是像这几季的《吸血鬼男子宿舍》、《百千家的妖怪王子》、《黄昏失焦》还有前几年的《偶像梦幻祭》这种偶像企划作品动画以及各种乙女游戏改动画。 \n\n我记得只有《idolish7偶像星愿》的动画没暴死。 \n\n然后我想到一个问题，补了一句“《黄昏失焦》（耽美）都不一定算作女性向，因为耽美跟","id":6,"tAvatar":"https://lain.bgm.tv/r/400/pic/user/l/000/77/10/771008.jpg?r=1714401797&hd=1","tImage":"","tName":"水薰叶","tUid":"actoralice","tUrl":"https://bgm.tv/rakuen/topic/group/402198","tid":"402198","time":1721279696383,"title":"什么是女性向？如何定义女性向？","type":1,"uid":"bangumi_muxi"},{"content":"一个人的暑假，我呆坐在空调房，无所事事。 \n\n   \n\n  其实我本可以不那么无聊的，比如我刚写了一个剧本，可以出门去拍。虽说是剧本，但内容大概是你刷抖音时，停留超不过三秒的那种程度。即便是这样，我的同伴一个个都事务繁忙而拒绝出席拍摄，唯一到场的摄影师，表示明天要上两周的软件课，不能再来。 \n\n  挺好，起码他有个充实的活动。 \n\n    \n\n\n  其实我本可以不那么无聊的，比如我电脑上下好了几款久负盛名的单机游戏，上面的游戏时长指向零。大部分是夏促推荐购买的，他们挂上了平日见不到的优惠。挺好，我要买，我不知道为什么我要买，但是他们挂上了平日见不到的优惠，所以，我要买。 \n\n  不知道从什么时","id":7,"tAvatar":"https://lain.bgm.tv/r/400/pic/user/l/000/66/80/668099.jpg?r=1674398542&hd=1","tImage":"","tName":"point.","tUid":"668099","tUrl":"https://bgm.tv/rakuen/topic/group/402229","tid":"402229","time":1721304876265,"title":"我正在度过一个无聊的暑假","type":1,"uid":"bangumi_muxi"},{"content":"刚刚无意间在一个帖子里发现还有新站，但是发现截止到现在已经有两年了，还是没有正式上线，就好奇想问下这个新站有计划什么时候正式上线吗？UI还挺好看的","id":8,"tAvatar":"https://lain.bgm.tv/r/400/pic/user/l/000/34/56/345617.jpg?r=1706375031&hd=1","tImage":"","tName":"无名的南瓜君","tUid":"wudipilihuo","tUrl":"https://bgm.tv/rakuen/topic/group/401859","tid":"401859","time":1721450291863,"title":"新站next.bgm.tv何时会上线呢？","type":1,"uid":"bangumi_muxi"},{"content":"rt，想找个稳定点的","id":9,"tAvatar":"https://lain.bgm.tv/r/400/pic/user/l/000/46/73/467323.jpg?r=1583708896","tImage":"","tName":"edpage","tUid":"edpageward","tUrl":"https://bgm.tv/rakuen/topic/group/402412","tid":"402412","time":1721801193722,"title":"现在有什么不错的在线追番站吗","type":1,"uid":"bangumi_muxi"},{"content":"跟群友聊过用bangumi的老ass们很少看动画KOL，但是毕竟国内动画圈就这么大，不看也多少听过。那么对于仍处于国内动画基本盘的b站动画区up，大伙都有什么看法呢？畅所欲言。","id":10,"tAvatar":"https://lain.bgm.tv/r/400/pic/user/l/000/56/49/564916.jpg?r=1704011059&hd=1","tImage":"","tName":"淡虚无幻","tUid":"564916","tUrl":"https://bgm.tv/rakuen/topic/group/402701","tid":"402701","time":1722166704366,"title":"大伙来评价一下B站动画区UP主","type":1,"uid":"bangumi_muxi"},{"content":"维基候选人不是我不点推荐，是槽点实在太多，每次私信也麻烦，在 @clinkz 的提议下干脆汇个总好了￼（施工中...） \nps. 推荐条件：新增有效条目1页以上：https://bgm.tv/user/你的id/wiki \n\n全体： \n1. 除更新话数未定外，不要保留星号* \n\n书籍： \n1. 连载书籍不管是小说还是漫画请勾选系列（除非已出版单行本且一本完结） \n2. 标题请用原文，日本的用日语，台湾的用繁体，日亚括号里的文库信息去掉 \n3. 漫画请自行添加“作者”或“作画”、“原作”、“脚本”，小说请添加“作者”、“插图”，具体的制作人员请用原文（bangumi人物条目名）且不保留空格 \n4","id":11,"tAvatar":"https://lain.bgm.tv/r/400/pic/user/l/000/02/18/21804.jpg?r=1686325224&hd=1","tImage":"","tName":"mizudiwood💿","tUid":"mizudiwood","tUrl":"https://bgm.tv/rakuen/topic/group/402872","tid":"402872","time":1722316185242,"title":"[WIKI] 常见编辑错误汇总","type":1,"uid":"bangumi_muxi"},{"content":"此贴用于统计ASMR音声🎧的资源网站 \n———————————————————————————————————————————— \nKikoeru：https://www.asmr.one/ \n备注：非常好用的在线网站，强烈推荐 ，免费无广告！！！（需要梯子） \n———————————————————————————————————————————— \neat_ASMR：https://eatasmr.com/ \n备注：免费的资源网站，需要每日签到获得E饼兑换粮票再兑换资源。（国内直连） \n———————————————————————————————————————————— \nASMR_","id":12,"tAvatar":"https://lain.bgm.tv/r/400/pic/user/l/000/35/13/351390.jpg?r=1672240450&hd=1","tImage":"","tName":"𝙇𝙤𝙨𝙩 𝙋𝙞𝙜 🎉","tUid":"lostpig","tUrl":"https://bgm.tv/rakuen/topic/group/374340","tid":"374340","time":1722735932758,"title":"ASMR音声资源网站的统计（R-18）","type":1,"uid":"bangumi_muxi"},{"content":"一款叫作 天地无用 的播客，感觉是自己听过的最好的acg相关的播客节目了。颇具情调的节目氛围，以讲述或对话进行的轻松诙谐又不失干货的节目形式，加上主持人3000老师那一口磁性嗓音，一年来不知陪我度过了多少寂寞的时光…可自今年4月底那期节目后便完全没了音讯，各大播客平台上也没有见停播的公告，可有听友知道发生了什么吗？￼ \n\n附上链接：https://xima.tv/1_h65I1c5?_sonic=0","id":13,"tAvatar":"https://lain.bgm.tv/r/400/pic/user/l/000/53/30/533060.jpg?r=1587043440","tImage":"","tName":"Clabpick","tUid":"cropbrick","tUrl":"https://bgm.tv/rakuen/topic/group/403251","tid":"403251","time":1722881252946,"title":"喜欢的播客不知为什么不更新了","type":1,"uid":"bangumi_muxi"},{"content":"￼","id":14,"tAvatar":"https://lain.bgm.tv/r/400/pic/user/l/000/75/35/753594.jpg?r=1672649229&hd=1","tImage":"","tName":"mbsxzj","tUid":"753594","tUrl":"https://bgm.tv/rakuen/topic/group/403253","tid":"403253","time":1722917158927,"title":"大佬们，有没有看漫画无删还很全的网站","type":1,"uid":"bangumi_muxi"},{"content":"春天来了，心情开始躁动不安，最近烦心事多，晚上又开始辗转反侧睡不着了，特别渴望变成妹子，然后被X，怀孕，抱小孩。总是幻想些奇怪的荒诞play。感觉应该就是性焦虑吧，三十多的人了，一个人在外面漂泊鬼混多年，事业一事无成，一个女朋友没正经谈过，十多年一直独居，昨天不知怎么突然想量量自己长高没有，结果只有172，这多年来不知为何一直认为自己176，给所有人都这么说的，知道真相一下破防了，感觉已经一无是处了￼","id":15,"tAvatar":"https://lain.bgm.tv/r/400/pic/user/l/000/22/21/222174.jpg?r=1416022064","tImage":"","tName":"为了道德","tUid":"vivids","tUrl":"https://bgm.tv/rakuen/topic/group/396025","tid":"396025","time":1723472544862,"title":"想要转性是不是性焦虑的一种表现","type":1,"uid":"bangumi_muxi"},{"content":"（有人能看到吗￼）有什么看过的作品都可以在下面留一下 符合条件的我都加进去 \n具有性转/tsf要素的作品收集【男变女 霓虹作品 不包括R18 持续更新】 \n包括但不限于 身体/灵魂互换 直接变/变身 异世界穿越/原世界重生 合体 附身 \n主线：主角性转，贯穿作品始终 \n浓度3：配角性转，贯穿作品始终 \n浓度2：有一个篇章以性转内容为主，其他不是【动画：3集及以上 小说：一卷及以上 漫画：10话及以上】 \n浓度1：只有部分性转场景 \n注明：轻小说分卷不纳入其中 但轻小说的web版条目和文库版可能同时存在 \n           人物部分 如果是身体互换且在你班是两个条目 那不加进此目录","id":16,"tAvatar":"https://lain.bgm.tv/r/400/pic/user/l/000/84/24/842400.jpg?r=1714888834&hd=1","tImage":"","tName":"レム","tUid":"842400","tUrl":"https://bgm.tv/rakuen/topic/group/403614","tid":"403614","time":1723521842046,"title":"建含tsf及性转要素的作品收集条目了 有符合要求要素就可以在留一下","type":1,"uid":"bangumi_muxi"},{"content":"电脑端有什么好用的 看漫画的软件，求推荐","id":17,"tAvatar":"https://lain.bgm.tv/r/400/pic/user/l/000/75/16/751625.jpg?r=1714116137&hd=1","tImage":"","tName":"九黎朴","tUid":"jiulipu","tUrl":"https://bgm.tv/rakuen/topic/group/403761","tid":"403761","time":1723734905851,"title":"电脑端有什么好用的 看漫画的软件","type":1,"uid":"bangumi_muxi"},{"content":"现在的维基协力楼是用户提出修改，然后由维基人进行编辑。 \n\n尝试减少 wiki 人在维基协力工作的工作量：现在通过这个网站支持由非维基人编辑维基，然后由维基人进行审核。 \n\nhttps://patch.bgm38.com/ \n\n真正把修改提交到网站的功能还需要进一步测试，暂时还没开放。 \n\n现在只开放了非维基人修改提交功能，以及维基人拒绝建议的功能 \n\n顺便需要一些UI建议...","id":18,"tAvatar":"https://lain.bgm.tv/r/400/pic/user/l/000/28/76/287622.jpg?r=1672779554&hd=1","tImage":"","tName":"bangumi大西王","tUid":"trim21","tUrl":"https://bgm.tv/rakuen/topic/group/403865","tid":"403865","time":1723903714585,"title":"抓点帕鲁测试一下（半成品的）新功能","type":1,"uid":"bangumi_muxi"},{"content":"先说说自己平时听音乐的习惯，主听JPOP、港乐、ACG(包括vocaloid，游戏ost)，欧美、KPOP、EDM最近听得少了。 \n数字版权时代很多歌曲的版权都分散在各种平台，以前我是网易云+QQ音乐+Spotify换着用，歌单都得拆开几份，后来发现国内的音乐平台会偷偷删掉你歌单里的收藏，原因有很多，例如版权到期了，或者是某个歌手被封杀了，又或者是某首歌突然变敏感了，总之就是你不主动备份的话连丢了哪些收藏都不知道，这对热爱音乐的人来说是很难受的。 \n所以从几年前我就开始备份歌单，因为主要用pc和手机(ios)听歌，所以我先把歌曲下载到电脑,再上传到网易云的音乐云盘，这样我歌单里的歌就自动关联云","id":19,"tAvatar":"https://lain.bgm.tv/r/400/pic/user/l/000/60/31/603171.jpg?r=1672404259&hd=1","tImage":"","tName":"Yoheao","tUid":"603171","tUrl":"https://bgm.tv/rakuen/topic/group/403184","tid":"403184","time":1723936470676,"title":"现在还有什么免费下载音乐的网站","type":1,"uid":"bangumi_muxi"},{"content":"用的kiwi装了油猴，想要再整点扩展，chrome应用商城里的，或者Greasy Fork的脚本都行","id":20,"tAvatar":"file:///android_asset/image/info_only.jpg","tImage":"","tName":"枕流","tUid":"796925","tUrl":"https://bgm.tv/rakuen/topic/group/403925","tid":"403925","time":1724811013513,"title":"有什么推荐的chrome扩展","type":1,"uid":"bangumi_muxi"},{"content":"我一直对《天气之子》情有独钟。要说它在诚哥的作品里并不是最突出的一个：论隽永诗意，有秒五；论故事流畅一气呵成，有君名。相比之下，本作显得粗粝，像是未经精细打磨就抛向观众的一块投石。而它也确实是新海诚作品中的异类：这是一个与“回忆”并无瓜葛的故事，并不存在前作序列中常见的那种暧昧感情和大量抒情性内心独白。这里的话语和行动都是关于当下的、鲜明的、决断性的。也因此，它获得了独特的气质，并且与这个时代密切相关。 \n\n“东京”之暗面：治理暴力与已然来临的危机 \n\n过往新海诚作品中对东京的呈现大多正面，往往是将其作为美丽的背景舞台。樱树缝隙中倾泻而下的灿烂阳光，阴雨连绵、诗意盎然的新宿御苑，三叶第一次交换","id":21,"tAvatar":"https://lain.bgm.tv/r/400/pic/user/l/000/72/85/728594.jpg?r=1673182665&hd=1","tImage":"","tName":"raskolnikov","tUid":"728594","tUrl":"https://bgm.tv/blog/343144","tid":"343144","time":1725551548386,"title":"一个关于当下的，“不正确的故事”","type":2,"uid":"bangumi_muxi"},{"content":"买了个VR，三天打了十四发，整个人都昏昏沉沉的，到健身房做了四组就困的像A片丈夫🐏","id":22,"tAvatar":"https://lain.bgm.tv/r/400/pic/user/l/000/52/95/529577.jpg?r=1672124225&hd=1","tImage":"","tName":"Kirotr","tUid":"529577","tUrl":"https://bgm.tv/rakuen/topic/group/404986","tid":"404986","time":1725551663622,"title":"胶打太多人打昏了","type":1,"uid":"bangumi_muxi"},{"content":"本工具可统计用户“标记为看过”的“动画”的wiki数据中，制作人员或声优的出现次数。 \n\n工具： \n67.py \n依赖： \n（用户收藏JSON的生成）：32.py \n（官方Archive的获取）：45.py 或者直接去官方仓库下 \n\n交互式食用： \n1. 用32.py下载用户收藏JSON。 \n2. 用45.py或直接去官方仓库下载最新的Archive并解压到同一目录 \n3. 运行67.py。先输入JSON文件名（路径），再输入模式（1为声优，2为制作人员）。 \n4. 前25个结果会打印在控制台。完整结果会输出为csv。声优模式输出的是cv_hits.csv，制作人员模式输出的是staff_hi","id":23,"tAvatar":"https://lain.bgm.tv/r/400/pic/user/l/000/71/00/710008.jpg?r=1693125817&hd=1","tImage":"","tName":"Jirehlov","tUid":"jirehlov","tUrl":"https://bgm.tv/rakuen/topic/group/405064","tid":"405064","time":1725707182809,"title":"【工具】统计用户看过动画命中的制作人员或声优","type":1,"uid":"bangumi_muxi"}]